{"is_source_file": true, "format": "JavaScript", "description": "This file is a Node.js script that serves as a build delegator, invoking a frontend build process in a CI environment for a tic-tac-toe project. It uses child_process to run an npm script within a specific workspace.", "external_files": ["child_process"], "external_methods": ["spawnSync"], "published": [], "classes": [], "methods": [{"name": "spawnSync", "description": "Method imported from child_process module to run command synchronously."}], "calls": ["spawnSync('npm', ['run', '--workspace', 'tic_tac_toe_frontend', 'build'])"], "search-terms": ["build script", "CI build", "tic-tac-toe frontend", "node spawnSync", "run-build"], "state": 2, "file_id": 40, "knowledge_revision": 99, "git_revision": "edd020a11bd84ce218772a2bf6b24f23335fd7f1", "ctags": [{"_type": "tag", "name": "res", "path": "/home/kavia/workspace/code-generation/tic-tac-toe-classic-145105-145114/run-build.js", "pattern": "/^const res = spawnSync('npm', ['run', '--workspace', 'tic_tac_toe_frontend', 'build'], {$/", "language": "JavaScript", "kind": "constant"}], "hash": "71a497db5207ce506d7c985babd1b9d9", "format-version": 4, "code-base-name": "tic_tac_toe_frontend", "filename": "run-build.js", "revision_history": [{"99": "edd020a11bd84ce218772a2bf6b24f23335fd7f1"}]}