{"is_source_file": true, "format": "TypeScript/React Native", "description": "This file defines a React functional component named Button that renders a customizable button supporting multiple variants, theming, and animated press interactions.", "external_files": ["../theme/ThemeContext", "../utils/animations"], "external_methods": ["useTheme", "Animate.pressScale"], "published": ["default", "Button"], "classes": [], "methods": [{"name": "Button", "description": "A memoized React functional component rendering a styled, animated button supporting theming and different visual variants."}], "calls": ["useTheme", "Animate.pressScale", "Pressable", "StyleSheet.create", "Animated.View", "Text"], "search-terms": ["React", "Button", "press animation", "themed button", "variant styles", "React Native", "TypeScript", "custom button component"], "state": 2, "file_id": 16, "knowledge_revision": 110, "git_revision": "cac8a8524a93b59ec17d4ac805de901827886b30", "revision_history": [{"41": ""}, {"84": "e1bcf5174902819906c071e410faab1e12561a2e"}, {"103": "27118743f394ec31ec8014a0d65db24163920eb7"}, {"110": "cac8a8524a93b59ec17d4ac805de901827886b30"}], "ctags": [], "hash": "7802c6b6f380154aa9d4a4a3d7dc130d", "format-version": 4, "code-base-name": "tic_tac_toe_frontend", "filename": "tic_tac_toe_frontend/src/components/Button.tsx"}