{"is_source_file": true, "format": "TypeScript/React JSX", "description": "This file defines the main application component for a React Native app, integrating theming, routing, and rendering different screens based on route state.", "external_files": ["./src/theme/ThemeContext", "./src/theme/InternalRouter", "./src/screens/HomeScreen", "./src/screens/GameScreen", "./src/screens/SettingsScreen", "./src/theme/routerTypes"], "external_methods": ["useRouter", "useMemo", "memo"], "published": ["default"], "classes": [], "methods": [{"name": "RouterOutlet", "description": "A memoized component that determines which screen to display based on the current route, and creates navigation objects with memoization for stable references."}, {"name": "App", "description": "Main exported component that provides theming and routing context for the entire app."}], "calls": ["useRouter()", "useMemo()", "memo()", "React.createElement (via JSX)"], "search-terms": ["RouterOutlet", "useRouter", "ThemeProvider", "InternalRouter", "screens", "Navigation", "React Native app"], "state": 2, "file_id": 3, "knowledge_revision": 117, "git_revision": "27118743f394ec31ec8014a0d65db24163920eb7", "revision_history": [{"13": "3713da17462f6705f6299075f23680fab6e4f4f8"}, {"15": "3713da17462f6705f6299075f23680fab6e4f4f8"}, {"52": "3713da17462f6705f6299075f23680fab6e4f4f8"}, {"56": "3713da17462f6705f6299075f23680fab6e4f4f8"}, {"63": "3713da17462f6705f6299075f23680fab6e4f4f8"}, {"79": "e1bcf5174902819906c071e410faab1e12561a2e"}, {"98": "27118743f394ec31ec8014a0d65db24163920eb7"}, {"117": "27118743f394ec31ec8014a0d65db24163920eb7"}], "ctags": [], "hash": "3a3d61f21793d142f17928e567213372", "format-version": 4, "code-base-name": "tic_tac_toe_frontend", "filename": "tic_tac_toe_frontend/App.tsx"}