{"is_source_file": true, "format": "TypeScript/React Native", "description": "A React Native functional component that renders a themed modal dialog with customizable visibility, close handler, style, and children content.", "external_files": ["../theme"], "external_methods": [], "published": ["default (ModalCard)"], "classes": [], "methods": [{"name": "ModalCard", "description": "A functional React component that shows a modal with a backdrop and styled card content."}], "calls": ["React", "Modal", "View", "StyleSheet.create"], "search-terms": ["ModalCard", "React Native", "Modal", "Card styling", "Custom modal"], "state": 2, "file_id": 34, "knowledge_revision": 83, "git_revision": "", "ctags": [], "hash": "0bc333936b8951daa7ef431ff6246afe", "format-version": 4, "code-base-name": "tic_tac_toe_frontend", "filename": "tic_tac_toe_frontend/src/components/ModalCard.tsx", "revision_history": [{"83": ""}]}