{"is_source_file": true, "format": "TypeScript (React TSX)", "description": "This file implements an internal lightweight router context for a React application, providing navigation methods (navigate, goBack) and managing route state with a React context.", "external_files": ["./routerTypes"], "external_methods": ["React.createContext", "React.useContext", "React.useCallback", "React.useState", "React.FC", "React.PropsWithChildren"], "published": ["useRouter", "InternalRouter"], "classes": [], "methods": [{"name": "useRouter", "description": "A custom hook to access the router context, throws an error if used outside the InternalRouter component."}, {"name": "InternalRouter", "description": "A React functional component that provides routing context to its children, managing a simple in-memory navigation stack."}], "calls": ["React.createContext", "React.useContext", "React.useCallback", "React.useState", "React.FC", "React.PropsWithChildren"], "search-terms": ["InternalRouter", "useRouter", "React Context", "navigation stack", "custom React hook", "routing"], "state": 2, "file_id": 25, "knowledge_revision": 80, "git_revision": "e1bcf5174902819906c071e410faab1e12561a2e", "revision_history": [{"54": ""}, {"80": "e1bcf5174902819906c071e410faab1e12561a2e"}], "ctags": [], "hash": "b45904b0477effc62220b0896b89fbad", "format-version": 4, "code-base-name": "tic_tac_toe_frontend", "filename": "tic_tac_toe_frontend/src/theme/InternalRouter.tsx"}